selsoup/__init__.py
selsoup/geckodriver.log
selsoup/selsoup.py
selsoup/xpaths.py
selsoup-0.2.11.dist-info/entry_points.txt
selsoup-0.2.11.dist-info/WHEEL
selsoup-0.2.11.dist-info/METADATA
selsoup-0.2.11.dist-info/RECORD
